testing_this_style/__init__.py
testing_this_style/testing_this_style.py
testing_this_style-0.0.1.dist-info/METADATA
testing_this_style-0.0.1.dist-info/WHEEL
testing_this_style-0.0.1.dist-info/top_level.txt
testing_this_style-0.0.1.dist-info/RECORD
