Metadata-Version: 2.1
Name: testing-this-style
Version: 0.0.1
Summary: Style analyzer
Home-page: UNKNOWN
Author: Test
Author-email: <youremail@email.com>
License: UNKNOWN
Keywords: python,test style
Platform: UNKNOWN
Classifier: Development Status :: 3 - Alpha
Classifier: Intended Audience :: Education
Classifier: Programming Language :: Python :: 2
Classifier: Programming Language :: Python :: 3
Classifier: Operating System :: MacOS :: MacOS X
Classifier: Operating System :: Microsoft :: Windows
Requires-Dist: spacy
Requires-Dist: en-core-web-lg
